setup.py
stat_gaussian_binomial_distributions/Binomialdistribution.py
stat_gaussian_binomial_distributions/Gaussiandistribution.py
stat_gaussian_binomial_distributions/Generaldistribution.py
stat_gaussian_binomial_distributions/__init__.py
stat_gaussian_binomial_distributions.egg-info/PKG-INFO
stat_gaussian_binomial_distributions.egg-info/SOURCES.txt
stat_gaussian_binomial_distributions.egg-info/dependency_links.txt
stat_gaussian_binomial_distributions.egg-info/not-zip-safe
stat_gaussian_binomial_distributions.egg-info/top_level.txt