Metadata-Version: 1.0
Name: stat-gaussian-binomial-distributions
Version: 0.2
Summary: Gaussian distributions and binomial distributions. This is a assignment package. If you are looking for  anything similar to this, then I don't recommend using this as this may contain bugs.
Home-page: UNKNOWN
Author: gns
Author-email: UNKNOWN
License: UNKNOWN
Platform: UNKNOWN
